arcli/__init__.py
arcli/__main__.py
arcli/config/__init__.py
arcli/config/base.py
arcli/exceptions/__init__.py
arcli/exceptions/base.py
arcli/terminal/__init__.py
arcli/terminal/cli.py
arcli/triggers/__init__.py
arcli/triggers/always.py
arcli/triggers/base.py
arcli/triggers/git.py
arcli/worker/__init__.py
arcli/worker/factory.py
arcli/worker/models/__init__.py
arcli/worker/models/enum.py
arcli/worker/models/models.py
arcli/worker/models/parsers.py
arcli/worker/models/util.py
arcli/worker/reader.py
arcli-0.1.1.dist-info/entry_points.txt
arcli-0.1.1.dist-info/LICENSE
arcli-0.1.1.dist-info/WHEEL
arcli-0.1.1.dist-info/METADATA
arcli-0.1.1.dist-info/RECORD
