Metadata-Version: 2.1
Name: arcli
Version: 0.1.1
Summary: A TravisCI inspired builder
Home-page: https://github.com/guiscaranse/arcli
License: Apache-2.0
Keywords: build,travisci,arcli
Author: Guilherme Scaranse
Requires-Python: >=3.6,<4.0
Classifier: License :: OSI Approved :: Apache Software License
Classifier: Programming Language :: Python :: 3
Classifier: Programming Language :: Python :: 3.6
Classifier: Programming Language :: Python :: 3.7
Classifier: Topic :: Software Development :: Build Tools
Classifier: Topic :: Software Development :: Libraries :: Python Modules
Requires-Dist: PyYAML (>=5.1.2,<6.0.0)
Requires-Dist: click (>=7.0,<8.0)
Requires-Dist: colorama (>=0.4.1,<0.5.0)
Requires-Dist: gitpython (>=2.1.13,<3.0.0)
Requires-Dist: pydantic[ujson] (>=0.31.1,<0.32.0)
Requires-Dist: semantic_version (>=2.6.0,<3.0.0)
Project-URL: Repository, https://github.com/guiscaranse/arcli
